Metadata-Version: 2.1
Name: passbolt-py
Version: 0.0.4
Summary: Python library for Passbolt
Home-page: https://github.com/bigouden/passbolt-py
License: MIT-0
Project-URL: Documentation, https://github.com/bigouden/passbolt-py/blob/main/README.md
Project-URL: Source, https://github.com/bigouden/passbolt-py
Project-URL: Tracker, https://github.com/bigouden/passbolt-py/issues
Classifier: Programming Language :: Python :: 3
Classifier: Operating System :: OS Independent
Requires-Python: >=3.6
Provides-Extra: all
Provides-Extra: test
